sonika_langchain_bot/__init__.py
sonika_langchain_bot/document_processor.py
sonika_langchain_bot/langchain_bot_agent.py
sonika_langchain_bot/langchain_clasificator.py
sonika_langchain_bot/langchain_class.py
sonika_langchain_bot/langchain_files.py
sonika_langchain_bot/langchain_models.py
sonika_langchain_bot/langchain_tools.py
sonika_langchain_bot/bot/__init__.py
sonika_langchain_bot/bot/models.py
sonika_langchain_bot/bot/multi_node_bot.py
sonika_langchain_bot/bot/state.py
sonika_langchain_bot/bot/nodes/__init__.py
sonika_langchain_bot/bot/nodes/base_node.py
sonika_langchain_bot/bot/nodes/executor_node.py
sonika_langchain_bot/bot/nodes/logger_node.py
sonika_langchain_bot/bot/nodes/output_node.py
sonika_langchain_bot/bot/nodes/planner_node.py
sonika_langchain_bot/bot/nodes/react_agent_node.py
sonika_langchain_bot/bot/nodes/validator_node.py
sonika_langchain_bot/orchestrator/__init__.py
sonika_langchain_bot/orchestrator/orchestrator_bot.py
sonika_langchain_bot/orchestrator/state.py
sonika_langchain_bot/orchestrator/nodes/__init__.py
sonika_langchain_bot/orchestrator/nodes/base_node.py
sonika_langchain_bot/orchestrator/nodes/chitchat_agent_node.py
sonika_langchain_bot/orchestrator/nodes/inner_executor.py
sonika_langchain_bot/orchestrator/nodes/inner_planner.py
sonika_langchain_bot/orchestrator/nodes/orchestrator_node.py
sonika_langchain_bot/orchestrator/nodes/policy_agent_node.py
sonika_langchain_bot/orchestrator/nodes/research_agent_node.py
sonika_langchain_bot/orchestrator/nodes/task_agent_node.py
sonika_langchain_bot/orchestrator/prompts/orchestrator_system.txt
sonika_langchain_bot/planner/__init__.py
sonika_langchain_bot/planner/planner_bot.py
sonika_langchain_bot/planner/state.py
sonika_langchain_bot/planner/nodes/__init__.py
sonika_langchain_bot/planner/nodes/action_executor.py
sonika_langchain_bot/planner/nodes/base_node.py
sonika_langchain_bot/planner/nodes/conversation_synthesizer.py
sonika_langchain_bot/planner/nodes/smart_orchestrator.py
sonika_langchain_bot-0.0.61.dist-info/licenses/LICENSE
sonika_langchain_bot-0.0.61.dist-info/METADATA
sonika_langchain_bot-0.0.61.dist-info/WHEEL
sonika_langchain_bot-0.0.61.dist-info/top_level.txt
sonika_langchain_bot-0.0.61.dist-info/RECORD
