Metadata-Version: 2.4
Name: sonika-langchain-bot
Version: 0.0.61
Summary: Agente langchain con LLM
Author: Erley Blanco Carvajal
License: MIT License
Classifier: Programming Language :: Python :: 3
Classifier: License :: OSI Approved :: MIT License
Classifier: Operating System :: OS Independent
Requires-Python: >=3.6
License-File: LICENSE
Requires-Dist: langchain-mcp-adapters==0.1.9
Requires-Dist: langchain-community==0.3.26
Requires-Dist: langchain-core==0.3.66
Requires-Dist: langchain-openai==0.3.24
Requires-Dist: langgraph==0.4.8
Requires-Dist: langgraph-checkpoint==2.1.0
Requires-Dist: langgraph-sdk==0.1.70
Requires-Dist: dataclasses-json==0.6.7
Requires-Dist: python-dateutil==2.9.0.post0
Requires-Dist: pydantic==2.11.7
Requires-Dist: faiss-cpu==1.11.0
Requires-Dist: pypdf==5.6.1
Requires-Dist: python-dotenv==1.0.1
Requires-Dist: typing_extensions==4.14.0
Requires-Dist: typing-inspect==0.9.0
Requires-Dist: PyPDF2==3.0.1
Requires-Dist: python-docx==1.2.0
Requires-Dist: openpyxl==3.1.5
Requires-Dist: python-pptx==1.0.2
Provides-Extra: dev
Requires-Dist: sphinx<9.0.0,>=8.1.3; extra == "dev"
Requires-Dist: sphinx-rtd-theme<4.0.0,>=3.0.1; extra == "dev"
Dynamic: author
Dynamic: classifier
Dynamic: description
Dynamic: description-content-type
Dynamic: license
Dynamic: license-file
Dynamic: provides-extra
Dynamic: requires-dist
Dynamic: requires-python
Dynamic: summary
